Metadata-Version: 2.1
Name: clearterminal
Version: 1.3.3.7
Summary: Clear your terminal with ONE COMMAND
Author-email: holinim@duck.com
